laila/__init__.py
laila-0.1.0.dist-info/LICENSE
laila-0.1.0.dist-info/METADATA
laila-0.1.0.dist-info/WHEEL
laila-0.1.0.dist-info/RECORD
