Metadata-Version: 2.1
Name: laila
Version: 0.1.0
Summary: Common utilities for LLM projects
License: MIT
Author: Ergin Soysal
Author-email: esoysal@gmail.com
Requires-Python: >=3.11,<4.0
Classifier: License :: OSI Approved :: MIT License
Classifier: Operating System :: OS Independent
Classifier: Programming Language :: Python :: 3
Classifier: Programming Language :: Python :: 3.11
Classifier: Programming Language :: Python :: 3.12
Classifier: Programming Language :: Python :: 3.13
